cyberrangecz/openstack_driver/__init__.py
cyberrangecz/openstack_driver/decorators.py
cyberrangecz/openstack_driver/open_stack_client.py
cyberrangecz/openstack_driver/open_stack_proxy.py
cyberrangecz/openstack_driver/utils.py
cyberrangecz/openstack_driver/templates/terraform-deploy-template.j2
cyberrangecz/openstack_driver/templates/terraform-provider-template.j2
cyberrangecz_openstack_lib-0.39.1.dist-info/LICENSE
cyberrangecz_openstack_lib-0.39.1.dist-info/METADATA
cyberrangecz_openstack_lib-0.39.1.dist-info/WHEEL
cyberrangecz_openstack_lib-0.39.1.dist-info/top_level.txt
cyberrangecz_openstack_lib-0.39.1.dist-info/RECORD
