Metadata-Version: 2.1
Name: cyberrangecz-openstack-lib
Version: 0.39.1
Summary: Openstack Driver
Author: cybersecurityhub.cz
Requires-Python: >=3
License-File: LICENSE
Requires-Dist: cyberrangecz-python-commons~=0.1.17
Requires-Dist: keystoneauth1
Requires-Dist: jinja2
Requires-Dist: netaddr
Requires-Dist: python-glanceclient>=2.17
Requires-Dist: python-keystoneclient>=3.22
Requires-Dist: python-neutronclient>=6.14
Requires-Dist: python-novaclient>=16.0
Requires-Dist: structlog
Requires-Dist: Jinja2
Requires-Dist: pycryptodome>=3.9
Requires-Dist: deepdiff
Requires-Dist: yamlize>=0.6
